Metadata-Version: 2.4
Name: adafruit-circuitpython-pathlib
Version: 1.0.3
Summary: Subset of the CPython module pathlib
Author-email: Adafruit Industries <circuitpython@adafruit.com>
License: MIT
Project-URL: Homepage, https://github.com/adafruit/Adafruit_CircuitPython_Pathlib
Keywords: adafruit,blinka,circuitpython,micropython,pathlib,path,pathlib,file,files,dir,folder,directory,filesystem
Classifier: Intended Audience :: Developers
Classifier: Topic :: Software Development :: Libraries
Classifier: Topic :: Software Development :: Embedded Systems
Classifier: Topic :: System :: Hardware
Classifier: License :: OSI Approved :: MIT License
Classifier: Programming Language :: Python :: 3
License-File: LICENSE
Requires-Dist: Adafruit-Blinka
Provides-Extra: optional
Dynamic: license-file
